berkeley500A.py
berkeley500A-0.1.1.dist-info/DESCRIPTION.rst
berkeley500A-0.1.1.dist-info/METADATA
berkeley500A-0.1.1.dist-info/RECORD
berkeley500A-0.1.1.dist-info/WHEEL
berkeley500A-0.1.1.dist-info/metadata.json
berkeley500A-0.1.1.dist-info/top_level.txt
