Metadata-Version: 2.0
Name: berkeley500A
Version: 0.1.1
Summary: API for Berkeley 500A delay generator
Home-page: https://github.com/smiddy/berkeley500A
Author: Markus J Schmidt
Author-email: schmidt@ifd.mavt.ethz.ch
License: GNU GPLv3+
Platform: any
Classifier: Development Status :: 4 - Beta
Classifier: Intended Audience :: Science/Research
Classifier: Topic :: Scientific/Engineering
Classifier: License :: OSI Approved :: GNU General Public License v3 or later (GPLv3+)
Classifier: Programming Language :: Python :: 3.4
Requires-Dist: pyserial (==2.7)
